[
  {
    "tipo": "caja",
    "nombre": "Caja Stock 1",
    "categoria": "Digimon",
    "idioma": "Español",
    "precio": 50,
    "stock": 10,
    "imagen": "img/cajas/digimon/1.png"
  },
  {
    "tipo": "caja",
    "nombre": "Caja Stock 2",
    "categoria": "Digimon",
    "idioma": "Español",
    "precio": 55,
    "stock": 10,
    "imagen": "img/cajas/digimon/2.png"
  },
  {
    "tipo": "caja",
    "nombre": "Caja Stock 3",
    "categoria": "One Piece",
    "idioma": "Español",
    "precio": 60,
    "stock": 10,
    "imagen": "img/cajas/one piece/1.png"
  },
  {
    "tipo": "caja",
    "nombre": "Caja Stock 4",
    "categoria": "One Piece",
    "idioma": "Español",
    "precio": 65,
    "stock": 10,
    "imagen": "img/cajas/one piece/2.png"
  },
  {
    "tipo": "caja",
    "nombre": "Caja Stock 5",
    "categoria": "Pokemon",
    "idioma": "Español",
    "precio": 70,
    "stock": 10,
    "imagen": "img/cajas/pokemon/1.png"
  },
  {
    "tipo": "caja",
    "nombre": "Caja Stock 6",
    "categoria": "Pokemon",
    "idioma": "Español",
    "precio": 75,
    "stock": 10,
    "imagen": "img/cajas/pokemon/2.png"
  },
  {
    "tipo": "caja",
    "nombre": "Caja Stock 7",
    "categoria": "Magic",
    "idioma": "Español",
    "precio": 80,
    "stock": 10,
    "imagen": "img/cajas/magic/1.png"
  },
  {
    "tipo": "caja",
    "nombre": "Caja Stock 8",
    "categoria": "Magic",
    "idioma": "Español",
    "precio": 85,
    "stock": 10,
    "imagen": "img/cajas/magic/2.png"
  },
  {
    "tipo": "caja",
    "nombre": "Caja Stock 9",
    "categoria": "Dragon Ball",
    "idioma": "Español",
    "precio": 90,
    "stock": 10,
    "imagen": "img/cajas/dragonball/1.png"
  },
  {
    "tipo": "caja",
    "nombre": "Caja Stock 10",
    "categoria": "Dragon Ball",
    "idioma": "Español",
    "precio": 95,
    "stock": 10,
    "imagen": "img/cajas/dragonball/2.png"
  },
  {
    "tipo": "caja",
    "nombre": "Caja Stock 11",
    "categoria": "Yugioh",
    "idioma": "Español",
    "precio": 100,
    "stock": 10,
    "imagen": "img/cajas/yugioh/1.png"
  },
  {
    "tipo": "caja",
    "nombre": "Caja Stock 12",
    "categoria": "Yugioh",
    "idioma": "Español",
    "precio": 105,
    "stock": 10,
    "imagen": "img/cajas/yugioh/2.png"
  },
  {
    "tipo": "carta",
    "nombre": "Carta Stock 1",
    "categoria": "Digimon",
    "idioma": "Español",
    "precio": 5,
    "stock": 8,
    "imagen": "img/cartas/digimon/1.png"
  },
  {
    "tipo": "carta",
    "nombre": "Carta Stock 2",
    "categoria": "Digimon",
    "idioma": "Español",
    "precio": 7,
    "stock": 8,
    "imagen": "img/cartas/digimon/1.png"
  },
  {
    "tipo": "carta",
    "nombre": "Carta Stock 3",
    "categoria": "Digimon",
    "idioma": "Español",
    "precio": 9,
    "stock": 8,
    "imagen": "img/cartas/digimon/1.png"
  },
  {
    "tipo": "carta",
    "nombre": "Carta Stock 4",
    "categoria": "Digimon",
    "idioma": "Español",
    "precio": 11,
    "stock": 8,
    "imagen": "img/cartas/digimon/2.png"
  },
  {
    "tipo": "carta",
    "nombre": "Carta Stock 5",
    "categoria": "Digimon",
    "idioma": "Español",
    "precio": 13,
    "stock": 8,
    "imagen": "img/cartas/digimon/3.jpg"
  },
  {
    "tipo": "carta",
    "nombre": "Carta Stock 6",
    "categoria": "One Piece",
    "idioma": "Español",
    "precio": 15,
    "stock": 8,
    "imagen": "img/cartas/onepiece/1.png"
  },
  {
    "tipo": "carta",
    "nombre": "Carta Stock 7",
    "categoria": "One Piece",
    "idioma": "Español",
    "precio": 17,
    "stock": 8,
    "imagen": "img/cartas/onepiece/2.jpg"
  },
  {
    "tipo": "carta",
    "nombre": "Carta Stock 8",
    "categoria": "One Piece",
    "idioma": "Español",
    "precio": 19,
    "stock": 8,
    "imagen": "img/cartas/onepiece/3.jpg"
  },
  {
    "tipo": "carta",
    "nombre": "Carta Stock 9",
    "categoria": "Pokemon",
    "idioma": "Español",
    "precio": 21,
    "stock": 8,
    "imagen": "img/cartas/pokemon/1.png"
  },
  {
    "tipo": "carta",
    "nombre": "Carta Stock 10",
    "categoria": "Pokemon",
    "idioma": "Español",
    "precio": 23,
    "stock": 8,
    "imagen": "img/cartas/pokemon/3.jpg"
  },
  {
    "tipo": "carta",
    "nombre": "Carta Stock 11",
    "categoria": "Pokemon",
    "idioma": "Español",
    "precio": 25,
    "stock": 8,
    "imagen": "img/cartas/pokemon/5.jpg"
  },
  {
    "tipo": "carta",
    "nombre": "Carta Stock 12",
    "categoria": "Pokemon",
    "idioma": "Español",
    "precio": 27,
    "stock": 8,
    "imagen": "img/cartas/pokemon/1.png"
  }
]
